app_creator/__init__.py
app_creator/cli.py
leila/__init__.py
leila/admin.py
leila/apps.py
leila/tests.py
leila/urls.py
leila/migrations/__init__.py
leila/models/__init__.py
leila/views/__init__.py
migrations/__init__.py
models/__init__.py
views/__init__.py
leila_django_app_creator-0.1.3.dist-info/METADATA
leila_django_app_creator-0.1.3.dist-info/WHEEL
leila_django_app_creator-0.1.3.dist-info/entry_points.txt
leila_django_app_creator-0.1.3.dist-info/top_level.txt
leila_django_app_creator-0.1.3.dist-info/RECORD
