Metadata-Version: 2.4
Name: leila-django-app-creator
Version: 0.1.3
Summary: Générateur de structure d'app Django personnalisée
Author: alphine2.0
Author-email: ouattaratchelourgo02@gmail.com
License: MIT
Classifier: Programming Language :: Python :: 3
Classifier: Framework :: Django
Classifier: License :: OSI Approved :: MIT License
Dynamic: author
Dynamic: author-email
Dynamic: classifier
Dynamic: description
Dynamic: description-content-type
Dynamic: license
Dynamic: summary
